tetsu/__init__.py
tetsu/box_helper.py
tetsu/cloudant_helper.py
tetsu/cos_helper.py
tetsu/db2_helper.py
tetsu/log_helper.py
tetsu/mime_helper.py
tetsu/root.pem
tetsu/scans.py
tetsu/tm1_helper.py
tetsu/workday_helper.py
tetsu-1.2.8.dist-info/METADATA
tetsu-1.2.8.dist-info/WHEEL
tetsu-1.2.8.dist-info/RECORD
