Metadata-Version: 2.4
Name: tetsu
Version: 1.2.8
Summary: A library of helper scripts for IBM DS&C
Author: Hassan Kenawi
Author-email: hkenawi@ibm.com
Requires-Python: >=3.10,<4.0
Classifier: Programming Language :: Python :: 3
Classifier: Programming Language :: Python :: 3.10
Classifier: Programming Language :: Python :: 3.11
Classifier: Programming Language :: Python :: 3.12
Classifier: Programming Language :: Python :: 3.13
Classifier: Programming Language :: Python :: 3.14
Requires-Dist: boxsdk (>=3.9.2,<4.0.0)
Requires-Dist: cryptography (>=45.0.7,<46.0.0)
Requires-Dist: ibm-cos-sdk (==2.14.2)
Requires-Dist: ibmcloudant (>=0.10.7,<0.11.0)
Requires-Dist: importlib-resources (>=6.5.2,<7.0.0)
Requires-Dist: jaydebeapi (>=1.2.3,<2.0.0)
Requires-Dist: pandas (>=2.1.4,<3.0.0)
Requires-Dist: pyyaml (>=6.0.2,<7.0.0)
Requires-Dist: requests (>=2.31.0,<3.0.0)
Requires-Dist: sqlalchemy (>=2.0.23,<3.0.0)
Requires-Dist: tm1py (>=2.0.3,<3.0.0)
Requires-Dist: truststore (>=0.10.1,<0.11.0)
Project-URL: Repository, https://github.ibm.com/finance-dsc/tetsu
